comfyapi/__init__.py
comfyapi/example.py
comfyapi/main.py
techtrash_comfyapi-0.4.0.dist-info/METADATA
techtrash_comfyapi-0.4.0.dist-info/WHEEL
techtrash_comfyapi-0.4.0.dist-info/licenses/LICENSE
techtrash_comfyapi-0.4.0.dist-info/RECORD
