Metadata-Version: 2.4
Name: TechTrash_comfyapi
Version: 0.4.0
Summary: A package to use the ComfyAPI
Author-email: Clapin Arthur <clapin.arthur@gmail.com>
License-Expression: MIT
License-File: LICENSE
Classifier: Operating System :: OS Independent
Classifier: Programming Language :: Python :: 3
Requires-Python: >=3.11
Requires-Dist: asyncio==4.0.0
Requires-Dist: boto3==1.40.73
Requires-Dist: botocore==1.40.73
Requires-Dist: jmespath==1.0.1
Requires-Dist: nvidia-ml-py==13.580.82
Requires-Dist: pynvml==13.0.1
Requires-Dist: python-dateutil==2.9.0.post0
Requires-Dist: s3transfer==0.14.0
Requires-Dist: six==1.17.0
Requires-Dist: techtrash-s3file==0.1.0
Requires-Dist: urllib3==2.5.0
